hightea/client/__init__.py
hightea/client/apiactions.py
hightea/client/datahandler.py
hightea/client/interface.py
hightea/client/smpdf.py
hightea_client-0.5.5.data/scripts/highteacli
hightea_client-0.5.5.dist-info/METADATA
hightea_client-0.5.5.dist-info/WHEEL
hightea_client-0.5.5.dist-info/top_level.txt
hightea_client-0.5.5.dist-info/RECORD
