Metadata-Version: 2.1
Name: hightea-client
Version: 0.5.5
Summary: Command line interface to hightea project
Home-page: https://github.com/HighteaCollaboration/hightea-client
Author: Hightea Collaboration
Author-email: hightea@hep.phy.cam.ac.uk
License: MIT
Requires-Python: >=3.7
Requires-Dist: numpy
Requires-Dist: requests
Requires-Dist: urllib3
Requires-Dist: pyyaml
